sia_excel/__init__.py
sia_excel/pandas_excel_writer.py
sia_excel-1.0.1.dist-info/METADATA
sia_excel-1.0.1.dist-info/WHEEL
sia_excel-1.0.1.dist-info/top_level.txt
sia_excel-1.0.1.dist-info/RECORD
